fronttracker/__init__.py
fronttracker/core.py
fronttracker/geometry.py
fronttracker-1.1.1.dist-info/licenses/LICENSE
fronttracker-1.1.1.dist-info/METADATA
fronttracker-1.1.1.dist-info/WHEEL
fronttracker-1.1.1.dist-info/top_level.txt
fronttracker-1.1.1.dist-info/RECORD
